RDAnalyzer/__init__.py
RDAnalyzer/analyzer.py
RDAnalyzer/set.py
RDAnalyzer/species.py
RDAnalyzer/tools.py
RDAnalyzer-0.0.9.dist-info/METADATA
RDAnalyzer-0.0.9.dist-info/WHEEL
RDAnalyzer-0.0.9.dist-info/top_level.txt
RDAnalyzer-0.0.9.dist-info/RECORD
