Metadata-Version: 2.1
Name: RDAnalyzer
Version: 0.0.9
Summary: A small example package
Author-email: Lunliang Ma <malunliang@westlake.edu.cn>, Tao Wang <twang@westlake.edu.cn>
Project-URL: Homepage, https://github.com/WestlakeUniversity-WangLab/RDAnalyzer
Classifier: Programming Language :: Python :: 3
Classifier: License :: OSI Approved :: MIT License
Classifier: Operating System :: OS Independent
Requires-Python: >=3.7
